Metadata-Version: 2.1
Name: steem
Version: 1.0.1
Summary: Official python steem library.
Home-page: https://github.com/steemit/steem-python
Author: Steemit
Author-email: john@steemit.com
License: MIT
Keywords: steem,steemit,cryptocurrency,blockchain
Platform: UNKNOWN
Classifier: Intended Audience :: Developers
Classifier: License :: OSI Approved :: MIT License
Classifier: Natural Language :: English
Classifier: Programming Language :: Python :: 3
Classifier: Programming Language :: Python :: 3.5
Classifier: Topic :: Software Development :: Libraries
Classifier: Topic :: Software Development :: Libraries :: Python Modules
Classifier: Development Status :: 4 - Beta
Provides-Extra: build
Provides-Extra: dev
Provides-Extra: test
